Metadata-Version: 2.1
Name: tziot
Version: 1.6
Summary: tziot sdk
Home-page: https://github.com/jdhxyy/tziot-python
Author: jdh99
Author-email: jdh821@163.com
License: UNKNOWN
Platform: UNKNOWN
